vault_bitwarden_client.py
vault_bitwarden_client-1.0.0.dist-info/entry_points.txt
vault_bitwarden_client-1.0.0.dist-info/WHEEL
vault_bitwarden_client-1.0.0.dist-info/METADATA
vault_bitwarden_client-1.0.0.dist-info/RECORD
