Metadata-Version: 2.1
Name: vault-bitwarden-client
Version: 1.0.0
Summary: Use Bitwarden to unlock Ansible vaults
Author: Philip Douglass
Author-email: philip@philipdouglass.com
Requires-Python: >=3.6.1,<4.0.0
Classifier: Programming Language :: Python :: 3
Classifier: Programming Language :: Python :: 3.10
Classifier: Programming Language :: Python :: 3.7
Classifier: Programming Language :: Python :: 3.8
Classifier: Programming Language :: Python :: 3.9
